CHANGELOG
MANIFEST.in
README
setup.cfg
setup.py
fysom/__init__.py
fysom.egg-info/PKG-INFO
fysom.egg-info/SOURCES.txt
fysom.egg-info/dependency_links.txt
fysom.egg-info/top_level.txt
fysom.egg-info/zip-safe
test/test_async_state_transition.py
test/test_callbacks.py
test/test_finished_state.py
test/test_garbage_collection.py
test/test_initialization.py
test/test_many_to_many.py
test/test_same_dst.py
test/test_state.py
test/test_unicode_literals.py
test/test_wildcard.py