Metadata-Version: 1.1
Name: fysom
Version: 2.1.3
Summary: pYthOn Finite State Machine
Home-page: https://github.com/mriehl/fysom
Author: Mansour Behabadi, Jake Gordon, Maximilien Riehl, Stefano
Author-email: mansour@oxplot.com, jake@codeincomplete.com, maximilien.riehl@gmail.com, 
License: MIT
Platform: UNKNOWN
Classifier: Development Status :: 5 - Production/Stable
Classifier: Intended Audience :: Developers
Classifier: License :: OSI Approved :: MIT License
Classifier: Programming Language :: Python
Classifier: Natural Language :: English
Classifier: Operating System :: OS Independent
Classifier: Topic :: Scientific/Engineering
